{
  "Item": "Crystal Infused Axe",
  "Tier": "D",
  "Level": "10",
  "Damage": "24.4018-31",
  "APS": "1.351.35",
  "DPS": "33.5025-42",
  "Type": "Axe",
  "TwoHanded": false,
  "Size": "2x3",
  "Rarity": "Satanic",
  "Stats": [
    {
      "stat": "+[125-180]% Enhanced Damage",
      "class": "stat-default"
    },
    {
      "stat": "+15% Chance for a Deadly Blow",
      "class": "stat-default"
    },
    {
      "stat": "+25% of target Defense ignored",
      "class": "stat-default"
    },
    {
      "stat": "Attack Damage increased by 10%",
      "class": "stat-default"
    },
    {
      "stat": "+3 Life After each Kill",
      "class": "stat-default"
    },
    {
      "stat": "+3 Mana After each Kill",
      "class": "stat-default"
    },
    {
      "stat": "Socketed (0-2)",
      "class": "stat-default"
    }
  ]
}
